LICENSE
README.md
setup.py
spideyx/__init__.py
spideyx/spideyx.py
spideyx.egg-info/PKG-INFO
spideyx.egg-info/SOURCES.txt
spideyx.egg-info/dependency_links.txt
spideyx.egg-info/entry_points.txt
spideyx.egg-info/requires.txt
spideyx.egg-info/top_level.txt
spideyx/modules/__init__.py
spideyx/modules/banner/__init__.py
spideyx/modules/banner/banner.py
spideyx/modules/config/__init__.py
spideyx/modules/config/config.py
spideyx/modules/extractor/__init__.py
spideyx/modules/extractor/extracter.py
spideyx/modules/help/__init__.py
spideyx/modules/help/help.py
spideyx/modules/jsScrapy/__init__.py
spideyx/modules/jsScrapy/jsScrapy.py
spideyx/modules/paramfuzzer/__init__.py
spideyx/modules/paramfuzzer/paramfuzzer.py
spideyx/modules/scraper/__init__.py
spideyx/modules/scraper/scraper.py
spideyx/modules/update/__init__.py
spideyx/modules/update/update.py
spideyx/modules/verify/__init__.py
spideyx/modules/verify/verify.py
spideyx/modules/version/__init__.py
spideyx/modules/version/version.py