Metadata-Version: 2.1
Name: spideyx
Version: 1.0.0
Summary: SpideyX - A Web Reconnaissance Penetration Testing tool for Penetration Testers and Ethical Hackers
Home-page: https://github.com/RevoltSecurities/SpideyX
Author: D. Sanjai Kumar
Author-email: bughunterz0047@gmail.com
License-File: LICENSE
Requires-Dist: aiofiles>=24.1.0
Requires-Dist: alive_progress>=3.1.4
Requires-Dist: appdirs>=1.4.4
Requires-Dist: art>=6.2
Requires-Dist: asyncclick>=8.1.7.2
Requires-Dist: beautifulsoup4>=4.11.1
Requires-Dist: colorama>=0.4.6
Requires-Dist: dicttoxml>=1.7.16
Requires-Dist: fake_useragent>=1.5.1
Requires-Dist: httpx>=0.27.2
Requires-Dist: PyYAML>=6.0.2
Requires-Dist: Requests>=2.32.3
Requires-Dist: rich>=13.8.1
Requires-Dist: tldextract>=5.1.2
Requires-Dist: urllib3>=1.26.18
Requires-Dist: yarl>=1.9.4
